npc_user_sim/__init__.py
npc_user_sim/requirements.txt
npc_user_sim/trabalho_fake/__init__.py
npc_user_sim/trabalho_fake/npc.py
npc_user_sim-3.0.1.dist-info/LICENSE
npc_user_sim-3.0.1.dist-info/METADATA
npc_user_sim-3.0.1.dist-info/WHEEL
npc_user_sim-3.0.1.dist-info/top_level.txt
npc_user_sim-3.0.1.dist-info/RECORD
