Metadata-Version: 2.1
Name: npc_user_sim
Version: 3.0.1
Summary: Esse pacote vai mudar tudo
Author-email: surprise <rodrigo.castal@fakeEmail.com>
Requires-Python: >=3.10
License-File: LICENSE
